{
  "end": "2154", 
  "name": "Proposed_Resolution_20-287.pdf", 
  "start": "2154", 
  "text": "COUNCIL OF THE DISTRICT OF COLUMBIA\nProposed Resolution 20-287 (Deemed Approved July 7, 2013)\n\n20 DCSTAT 2154\n\nA PROPOSED RESOLUTION\n\nReferred\nMay 22, 2013\n\nTo confirm the appointment of Mr. Sean L. Ponder to the District of Columbia Boxing and Wrestling\nCommission.\n\nRESOLVED, BY THE COUNCIL OF THE DISTRICT OF COLUMBIA, That this\nresolution may be cited as the \"District of Columbia Boxing and Wrestling Commission Sean L.\nPonder Confirmation Resolution of 2013\".\n\nSec. 2. The Council of the District of Columbia confirms the appointment of:\nSean L. Ponder\n813 5th Street, NE, #3\nWashington, D.C. 20002\n(Ward 6)\nas a member of the District of Columbia Boxing and Wrestling Commission, established by\nsection 5 of the District of Columbia Boxing and Wrestling Commission Act, effective October\n8, 1975 (D.C. Law 1-20; D.C. Official Code \u00a7 3-604), and pursuant to section 2 of the\nConfirmation Act of 1978, effective March 3, 1979 (D.C. Law 2-142; D. C. Official Code\u00a7 1523.01), replacing Viraj V. Gandhi, for a term to end January 5, 2016.\nSec. 3. The Secretary to the Council of the District of Columbia shall transmit a copy of\nthis resolution, upon its adoption, each to the nominee and to the Office of the Mayor.\nSec. 4. This resolution shall take effect immediately.\n\nDistrict of\nColumbia\nBoxing and\nWrestling\nCommission\nSean L.\nPonder\nConfirmation\nResolution of\n2013\n\n\f", 
  "title": "District of Columbia Boxing and Wrestling Commission Sean L. Ponder Confirmation Resolution of 2013", 
  "council_period": "20"
}