{
  "end": "4725", 
  "name": "Proposed_Resolution_20-983.pdf", 
  "start": "4725", 
  "text": "COUNCIL OF THE DISTRICT OF COLUMBIA\nProposed Resolution 20-983 (Deemed Approved November 8, 2014)\n\n20 DCSTAT 4725\n\nA PROPOSED RESOLUTION\n\nOfficially Read\nSeptember 23,\n2014\n\nTo confirm the re-appointment of Mr. Constantin C. Rodousakis to the Board of Industrial Trades.\n\nRESOLVED, BY THE COUNCIL OF THE DISTRICT OF COLU MBIA, That this\nresolution may be cited as the \"Board of Industrial Trades Constantin C. Rodousakis\nReappointment Resolution of 2014\".\nSec. 2. The Council of the District of Columbia confirms the re-appointment of:\nConstantin C. Rodousakis\n4618 38th Street, N.W.\nWashington, D.C. 20016\n(Ward 3)\nas a licensed electrician member of the Board, established by section 1002(b) of the Second\nOmnibus Regulatory Reform Amendment Act of 1998, effective April 20, 1999 (D.C. Law 12261; D.C. Official Code \u00a7 47-2853.06(d)), and pursuant to section 2(f)(39) of the Confirmation\nAct of 1978, effective March 3, 1979 (D.C. Law 2-142; D. C. Official Code \u00a7 1-523.01(f)(39)),\nfor a term to end June 26, 2017.\nSec. 3. The Council of the District of Columbia shall transmit a copy of this resolution,\nupon its adoption, each to the nominee and to the Office of the Mayor.\nSec. 4. This resolution shall take effect immediately.\n\nBoard of\nIndustrial\nTrades\nConstantin C.\nRodousakis\nReappointment\nResolution of\n2014\n\n\f", 
  "title": "Board of Industrial Trades Constantin C. Rodousakis Reappointment Resolution of 2014", 
  "council_period": "20"
}